<?xml version="1.0" encoding="UTF-8"?>
<museScore version="3.01">
  <MenuBar>
    <Menu name="menu-file">
      <action>startcenter</action>
      <action>file-new</action>
      <action>file-open</action>
      <Menu name="menu-open-recent">
        </Menu>
      <action></action>
      <action>file-save</action>
      <action>file-save-as</action>
      <action>file-save-a-copy</action>
      <action>file-save-selection</action>
      <action>file-save-online</action>
      <action>file-export</action>
      <action>file-part-export</action>
      <action>file-import-pdf</action>
      <action></action>
      <action>file-close</action>
      <action></action>
      <action>parts</action>
      <action></action>
      <action>edit-info</action>
      <action></action>
      <action>print</action>
      <action></action>
      <action>quit</action>
      </Menu>
    <Menu name="menu-edit">
      <action>undo</action>
      <action>redo</action>
      <action></action>
      <action>cut</action>
      <action>copy</action>
      <action>paste</action>
      <action>paste-half</action>
      <action>paste-double</action>
      <action>swap</action>
      <action>delete</action>
      <action></action>
      <action>select-all</action>
      <action>select-section</action>
      <action>find</action>
      <action></action>
      <action>instruments</action>
      <action></action>
      <action>preference-dialog</action>
      </Menu>
    <Menu name="menu-view">
      <action>toggle-palette</action>
      <action>masterpalette</action>
      <action>inspector</action>
      <action>omr</action>
      <action>toggle-playpanel</action>
      <action>toggle-navigator</action>
      <action>toggle-timeline</action>
      <action>toggle-mixer</action>
      <action>synth-control</action>
      <action>toggle-selection-window</action>
      <action>toggle-piano</action>
      <action>toggle-scorecmp-tool</action>
      <action></action>
      <action>zoomin</action>
      <action>zoomout</action>
      <action></action>
      <Menu name="menu-toolbars">
        <action>toggle-fileoperations</action>
        <action>toggle-transport</action>
        <action>toggle-concertpitch</action>
        <action>toggle-imagecapture</action>
        <action>toggle-noteinput</action>
        <action>toggle-feedback</action>
        <action></action>
        <action>edit-toolbars</action>
        </Menu>
      <Menu name="menu-workspaces">
        </Menu>
      <action>toggle-statusbar</action>
      <action></action>
      <action>split-h</action>
      <action>split-v</action>
      <action></action>
      <action>show-invisible</action>
      <action>show-unprintable</action>
      <action>show-frames</action>
      <action>show-pageborders</action>
      <action>mark-irregular</action>
      <action></action>
      <action>fullscreen</action>
      </Menu>
    <Menu name="menu-add">
      <Menu name="menu-add-pitch">
        <action>note-input</action>
        <action></action>
        <action>note-c</action>
        <action>note-d</action>
        <action>note-e</action>
        <action>note-f</action>
        <action>note-g</action>
        <action>note-a</action>
        <action>note-b</action>
        <action></action>
        <action>chord-c</action>
        <action>chord-d</action>
        <action>chord-e</action>
        <action>chord-f</action>
        <action>chord-g</action>
        <action>chord-a</action>
        <action>chord-b</action>
        </Menu>
      <Menu name="menu-add-interval">
        <action>interval1</action>
        <action>interval2</action>
        <action>interval3</action>
        <action>interval4</action>
        <action>interval5</action>
        <action>interval6</action>
        <action>interval7</action>
        <action>interval8</action>
        <action>interval9</action>
        <action></action>
        <action>interval-2</action>
        <action>interval-3</action>
        <action>interval-4</action>
        <action>interval-5</action>
        <action>interval-6</action>
        <action>interval-7</action>
        <action>interval-8</action>
        <action>interval-9</action>
        </Menu>
      <Menu name="menu-tuplet">
        <action>duplet</action>
        <action>triplet</action>
        <action>quadruplet</action>
        <action>quintuplet</action>
        <action>sextuplet</action>
        <action>septuplet</action>
        <action>octuplet</action>
        <action>nonuplet</action>
        <action>tuplet-dialog</action>
        </Menu>
      <action></action>
      <Menu name="menu-add-measures">
        <action>insert-measure</action>
        <action>insert-measures</action>
        <action></action>
        <action>append-measure</action>
        <action>append-measures</action>
        </Menu>
      <Menu name="menu-add-frames">
        <action>insert-hbox</action>
        <action>insert-vbox</action>
        <action>insert-textframe</action>
        <action></action>
        <action>append-hbox</action>
        <action>append-vbox</action>
        <action>append-textframe</action>
        </Menu>
      <Menu name="menu-add-text">
        <action>title-text</action>
        <action>subtitle-text</action>
        <action>composer-text</action>
        <action>poet-text</action>
        <action>part-text</action>
        <action></action>
        <action>system-text</action>
        <action>staff-text</action>
        <action>expression-text</action>
        <action>chord-text</action>
        <action>rehearsalmark-text</action>
        <action>instrument-change-text</action>
        <action>fingering-text</action>
        <action></action>
        <action>lyrics</action>
        <action>sticking-text</action>
        <action>figured-bass</action>
        <action>tempo</action>
        </Menu>
      <Menu name="menu-add-lines">
        <action>add-slur</action>
        <action>add-hairpin</action>
        <action>add-hairpin-reverse</action>
        <action>add-8va</action>
        <action>add-8vb</action>
        <action>add-noteline</action>
        </Menu>
      </Menu>
    <Menu name="menu-format">
      <action>edit-style</action>
      <action>page-settings</action>
      <action></action>
      <action>add-remove-breaks</action>
      <Menu name="menu-stretch">
        <action>stretch+</action>
        <action>stretch-</action>
        <action>reset-stretch</action>
        </Menu>
      <action></action>
      <action>reset-style</action>
      <action>reset-beammode</action>
      <action>reset</action>
      <action></action>
      <action></action>
      <action>load-style</action>
      <action>save-style</action>
      </Menu>
    <Menu name="menu-tools">
      <action>transpose</action>
      <action></action>
      <action>explode</action>
      <action>implode</action>
      <Menu name="menu-voices">
        <action>voice-x12</action>
        <action>voice-x13</action>
        <action>voice-x14</action>
        <action>voice-x23</action>
        <action>voice-x24</action>
        <action>voice-x34</action>
        </Menu>
      <Menu name="menu-measure">
        <action>split-measure</action>
        <action>join-measures</action>
        </Menu>
      <action>time-delete</action>
      <action></action>
      <action>slash-fill</action>
      <action>slash-rhythm</action>
      <action></action>
      <action>pitch-spell</action>
      <action>reset-groupings</action>
      <action>resequence-rehearsal-marks</action>
      <action>unroll-repeats</action>
      <action></action>
      <action>copy-lyrics-to-clipboard</action>
      <action>fotomode</action>
      <action>del-empty-measures</action>
      </Menu>
    <Menu name="menu-plugins">
      <action>plugin-manager</action>
      <action>plugin-creator</action>
      <action></action>
      </Menu>
    <action></action>
    <Menu name="menu-help">
      <action>online-handbook</action>
      <Menu name="menu-tours">
        <action>show-tours</action>
        <action>reset-tours</action>
        </Menu>
      <action></action>
      <action>about</action>
      <action>about-qt</action>
      <action>about-musicxml</action>
      <action></action>
      <action>ask-help</action>
      <action>report-bug</action>
      <action>leave-feedback</action>
      <action></action>
      <action>resource-manager</action>
      <action></action>
      <action>revert-factory</action>
      </Menu>
    </MenuBar>
  </museScore>
